windmillendpointv1/__init__.py
windmillendpointv1/client/__init__.py
windmillendpointv1/client/endpoint_api.py
windmillendpointv1/client/endpoint_api_deploy_job.py
windmillendpointv1/client/endpoint_api_deployment.py
windmillendpointv1/client/endpoint_api_endpoint_hub.py
windmillendpointv1/client/endpoint_client.py
windmillendpointv1/client/endpoint_monitor_client.py
windmillendpointv1/client/getter.py
windmillendpointv1/client/evaluator/__init__.py
windmillendpointv1/client/evaluator/evaluator.py
windmillendpointv1/client/gaea/__init__.py
windmillendpointv1/client/gaea/api.py
windmillendpointv1/client/gaea/example.py
windmillendpointv1/client/gaea/infer.py
windmill_endpoint-1.0.0.25.dist-info/METADATA
windmill_endpoint-1.0.0.25.dist-info/WHEEL
windmill_endpoint-1.0.0.25.dist-info/top_level.txt
windmill_endpoint-1.0.0.25.dist-info/RECORD
